hero24/algorithms/__init__.py
hero24/algorithms/setup.py
hero24/algorithms/compression/__init__.py
hero24/algorithms/compression/lzw.py
hero24/algorithms/cryptography/__init__.py
hero24/algorithms/cryptography/adfgx.py
hero24/algorithms/cryptography/alberti_disc.py
hero24/algorithms/cryptography/caesar_cipher.py
hero24/algorithms/cryptography/enigma.py
hero24/algorithms/cryptography/playfair_cipher.py
hero24/algorithms/cryptography/tabula_recta.py
hero24/algorithms/cryptography/vigenere.py
hero24/algorithms/hero24/algorithms/egg-info/PKG-INFO
hero24/algorithms/hero24/algorithms/egg-info/SOURCES.txt
hero24/algorithms/hero24/algorithms/egg-info/dependency_links.txt
hero24/algorithms/hero24/algorithms/egg-info/top_level.txt
hero24/algorithms/maths/__init__.py
hero24/algorithms/maths/fibonacci.py
hero24/algorithms/maths/sieve_eratosthenes.py
hero24/algorithms/maths/sieve_sundaram.py
hero24/algorithms/searching/__init__.py
hero24/algorithms/searching/sequential_search.py
hero24/algorithms/sorting/__init__.py
hero24/algorithms/sorting/bubble_sort.py
hero24/algorithms/sorting/insertion_sort.py
hero24/algorithms/sorting/merge_sort.py
hero24/algorithms/sorting/selection_sort.py
hero24.algorithms-1.0.dist-info/METADATA
hero24.algorithms-1.0.dist-info/WHEEL
hero24.algorithms-1.0.dist-info/top_level.txt
hero24.algorithms-1.0.dist-info/RECORD
